README.md
setup.py
zyxel3525Api/__init__.py
zyxel3525Api/zyxel3525Api.py
zyxel3525Api.egg-info/PKG-INFO
zyxel3525Api.egg-info/SOURCES.txt
zyxel3525Api.egg-info/dependency_links.txt
zyxel3525Api.egg-info/requires.txt
zyxel3525Api.egg-info/top_level.txt